polars_mas/__init__.py
polars_mas/analysis.py
polars_mas/cli.py
polars_mas/config.py
polars_mas/constants.py
polars_mas/main.py
polars_mas/models.py
polars_mas/pipeline.py
polars_mas/postprocessing.py
polars_mas/preprocessing.py
polars_mas/data/phecode_definitions1.2.csv
polars_mas/data/sex2.csv
polars_mas-0.3.0.dist-info/METADATA
polars_mas-0.3.0.dist-info/WHEEL
polars_mas-0.3.0.dist-info/entry_points.txt
polars_mas-0.3.0.dist-info/RECORD
