Metadata-Version: 2.4
Name: polars-mas
Version: 0.3.0
Summary: polars-mas - a fast multiple association library for python backed by polars
Requires-Python: >=3.11
Requires-Dist: firthmodels[numba]>=0.4.0
Requires-Dist: loguru>=0.7.2
Requires-Dist: polars>=1.9.0
Requires-Dist: pyarrow>=22.0.0
Requires-Dist: statsmodels>=0.14.4
